Project1/part1.v
module register #(
parameter NBits = 16
) (
  input               clk,
  input[1:0]          funsel, 
  input               e, 
  input[NBits-1: 0]   i,
  output[NBits-1: 0]  q
);

reg[NBits-1:0] data;
assign q = data;

always @(posedge clk) begin
  if (e)
    case (funsel)
      2'b00: data = {NBits{1'b0}};  // Clear
      2'b01: data = i;              // Load
      2'b10: data = data - 1'b1;    // Decrement
      2'b11: data = data + 1'b1;    // Increment
    endcase
end 

endmodule

Project1/part2c.v
`include "part1.v"

module ARF(
  input           clk,
  input[7:0]      i,
  input[1:0]      out_b_sel,
  input[1:0]      out_a_sel,
  input[1:0]      funsel,
  input[3:0]      r_sel,
  output reg[7:0] out_a,
  output reg[7:0] out_b
);

  reg dclk;

  register #(.NBits(8)) PC (
    .clk    (dclk),
    .funsel (funsel),
    .i      (i     )
  );

  register #(.NBits(8)) AR (
    .clk    (dclk),
    .funsel (funsel),
    .i      (i     )
  );

  register #(.NBits(8)) SP (
    .clk    (dclk),
    .funsel (funsel),
    .i      (i     )
  );

  register #(.NBits(8)) PC_past (
    .clk    (dclk),
    .funsel (funsel),
    .i      (i     )
  );

  assign {AR.e,  SP.e, PC_past.e, PC.e} = r_sel;

  always @(posedge clk) begin
    dclk = 0;
    case (out_a_sel)
      2'b00: out_a = AR.q;
      2'b01: out_a = SP.q;
      2'b10: out_a = PC_past.q;
      2'b11: out_a = PC.q;
    endcase
    
    case (out_b_sel)
      2'b00: out_b = AR.q;
      2'b01: out_b = SP.q;
      2'b10: out_b = PC_past.q;
      2'b11: out_b = PC.q;
    endcase

    #1;
    dclk = 1;
  end

endmodule

Project1/part2c_tb.v
`include "part2c.v"

module part2c_tb;
  integer seed = 315001;
  reg clk;
  reg[7:0] i;
  reg[1:0] out_a_sel, out_b_sel, funsel;
  reg[3:0] r_sel;
  wire[7:0] out_a, out_b;

  ARF uut(
    .clk(clk),
    .i(i),
    .out_a_sel(out_a_sel),
    .out_b_sel(out_b_sel),
    .funsel(funsel),
    .r_sel(r_sel),
    .out_a(out_a),
    .out_b(out_b)
  );
  
  task displayHead;
    $display("%8s %6s %6s %6s %6s %6s %6s", "Input", "FunSel", "RSel","AR", "SP", "PCPrev", "PC");
  endtask

  task showRegistersThroughA; 
  begin
    $write("A:%6h %6b %6b ", i, funsel, r_sel);
    out_a_sel = 2'b00;
    repeat(4) begin
      #10;
      $write("%6h ", out_a);
      out_a_sel = out_a_sel + 1;
    end
    $display;
  end
  endtask

  task showRegistersThroughB; 
  begin
    $write("B:%6h %6b %6b ", i, funsel, r_sel);
    out_b_sel = 2'b00;
    repeat(4) begin
      #10;
      $write("%6h ", out_b);
      out_b_sel = out_b_sel + 1;
    end
    $display;
  end
  endtask

  task displayLine;
    $display({50{"-"}});
  endtask

  task showAll;
  begin
    displayLine;
    displayHead;
    showRegistersThroughA;
    showRegistersThroughB;
  end
  endtask

  always #5 clk = ~clk;

  initial begin
    $dumpfile("dump.vcd"); $dumpvars;
    $display("Testing adress register file (ARF)");
    clk = 0;

    $display("\nClear test");
    funsel = 2'b00;
    r_sel = 4'b1111;
    #10;
    showAll;

    $display("\nLoad with random numbers test:");
    funsel = 2'b01;
    
    r_sel = 4'b1000; i = $urandom(seed)%(256); #10;
    showAll;

    r_sel = 4'b0100; i = $urandom(seed)%(256); #10;
    showAll;
    
    r_sel = 4'b0010; i = $urandom(seed)%(256); #10;
    showAll;
    
    r_sel = 4'b0001; i = $urandom(seed)%(256); #10;
    showAll;

    $display("\nIncrement with random numbers test:");
    displayLine;
    funsel = 2'b11;
    displayHead;
    repeat(15) begin
      r_sel = $urandom(seed)%(64); #10;
      r_sel = 0;
      showRegistersThroughA;
    end

    $display("\nDecrement with random numbers test:");
    displayLine;
    funsel = 2'b10;
    displayHead;
    repeat(15) begin
      r_sel = $urandom(seed)%(64); #10;
      r_sel = 0;
      showRegistersThroughB;
    end

    $finish;
  end

endmodule

Project1/dump.vcd
$date
	Sun Apr  9 18:33:37 2023
$end
$version
	Icarus Verilog
$end
$timescale
	1s
$end
$scope module part2c_tb $end
$var wire 8 ! out_b [7:0] $end
$var wire 8 " out_a [7:0] $end
$var reg 1 # clk $end
$var reg 2 $ funsel [1:0] $end
$var reg 8 % i [7:0] $end
$var reg 2 & out_a_sel [1:0] $end
$var reg 2 ' out_b_sel [1:0] $end
$var reg 4 ( r_sel [3:0] $end
$var integer 32 ) seed [31:0] $end
$scope module uut $end
$var wire 1 # clk $end
$var wire 2 * funsel [1:0] $end
$var wire 8 + i [7:0] $end
$var wire 2 , out_a_sel [1:0] $end
$var wire 2 - out_b_sel [1:0] $end
$var wire 4 . r_sel [3:0] $end
$var reg 1 / dclk $end
$var reg 8 0 out_a [7:0] $end
$var reg 8 1 out_b [7:0] $end
$scope module AR $end
$var wire 1 / clk $end
$var wire 1 2 e $end
$var wire 2 3 funsel [1:0] $end
$var wire 8 4 i [7:0] $end
$var wire 8 5 q [7:0] $end
$var parameter 32 6 NBits $end
$var reg 8 7 data [7:0] $end
$upscope $end
$scope module PC $end
$var wire 1 / clk $end
$var wire 1 8 e $end
$var wire 2 9 funsel [1:0] $end
$var wire 8 : i [7:0] $end
$var wire 8 ; q [7:0] $end
$var parameter 32 < NBits $end
$var reg 8 = data [7:0] $end
$upscope $end
$scope module PC_past $end
$var wire 1 / clk $end
$var wire 1 > e $end
$var wire 2 ? funsel [1:0] $end
$var wire 8 @ i [7:0] $end
$var wire 8 A q [7:0] $end
$var parameter 32 B NBits $end
$var reg 8 C data [7:0] $end
$upscope $end
$scope module SP $end
$var wire 1 / clk $end
$var wire 1 D e $end
$var wire 2 E funsel [1:0] $end
$var wire 8 F i [7:0] $end
$var wire 8 G q [7:0] $end
$var parameter 32 H NBits $end
$var reg 8 I data [7:0] $end
$upscope $end
$upscope $end
$scope task displayHead $end
$upscope $end
$scope task displayLine $end
$upscope $end
$scope task showAll $end
$upscope $end
$scope task showRegistersThroughA $end
$upscope $end
$scope task showRegistersThroughB $end
$upscope $end
$upscope $end
$enddefinitions $end
$comment Show the parameter values. $end
$dumpall
b1000 H
b1000 B
b1000 <
b1000 6
$end
#0
$dumpvars
bx I
bx G
bx F
b0 E
1D
bx C
bx A
bx @
b0 ?
1>
bx =
bx ;
bx :
b0 9
18
bx 7
bx 5
bx 4
b0 3
12
bx 1
bx 0
x/
b1111 .
bx -
bx ,
bx +
b0 *
b1001100111001111001 )
b1111 (
bx '
bx &
bx %
b0 $
0#
bx "
bx !
$end
#5
0/
1#
#6
b0 ;
b0 =
b0 5
b0 7
b0 G
b0 I
b0 A
b0 C
1/
#10
0#
b0 &
b0 ,
#15
b0 "
b0 0
0/
1#
#16
1/
#20
0#
b1 &
b1 ,
#25
0/
1#
#26
1/
#30
0#
b10 &
b10 ,
#35
0/
1#
#36
1/
#40
0#
b11 &
b11 ,
#45
0/
1#
#46
1/
#50
0#
b0 '
b0 -
b0 &
b0 ,
#55
b0 !
b0 1
0/
1#
#56
1/
#60
0#
b1 '
b1 -
#65
0/
1#
#66
1/
#70
0#
b10 '
b10 -
#75
0/
1#
#76
1/
#80
0#
b11 '
b11 -
#85
0/
1#
#86
1/
#90
0D
0>
08
0#
b100001 %
b100001 +
b100001 4
b100001 :
b100001 @
b100001 F
b10000110011100111101111100110 )
b1000 (
b1000 .
b1 $
b1 *
b1 3
b1 9
b1 ?
b1 E
b0 '
b0 -
#95
0/
1#
#96
b100001 5
b100001 7
1/
#100
0#
#105
b100001 !
b100001 1
b100001 "
b100001 0
0/
1#
#106
1/
#110
0#
b1 &
b1 ,
#115
b0 "
b0 0
0/
1#
#116
1/
#120
0#
b10 &
b10 ,
#125
0/
1#
#126
1/
#130
0#
b11 &
b11 ,
#135
0/
1#
#136
1/
#140
0#
b0 &
b0 ,
#145
b100001 "
b100001 0
0/
1#
#146
1/
#150
0#
b1 '
b1 -
#155
b0 !
b0 1
0/
1#
#156
1/
#160
0#
b10 '
b10 -
#165
0/
1#
#166
1/
#170
0#
b11 '
b11 -
#175
0/
1#
#176
1/
#180
02
1D
0#
b11011011 %
b11011011 +
b11011011 4
b11011011 :
b11011011 @
b11011011 F
b1101101100010011110010100101111 )
b100 (
b100 .
b0 '
b0 -
#185
b100001 !
b100001 1
0/
1#
#186
b11011011 G
b11011011 I
1/
#190
0#
#195
0/
1#
#196
1/
#200
0#
b1 &
b1 ,
#205
b11011011 "
b11011011 0
0/
1#
#206
1/
#210
0#
b10 &
b10 ,
#215
b0 "
b0 0
0/
1#
#216
1/
#220
0#
b11 &
b11 ,
#225
0/
1#
#226
1/
#230
0#
b0 &
b0 ,
#235
b100001 "
b100001 0
0/
1#
#236
1/
#240
0#
b1 '
b1 -
#245
b11011011 !
b11011011 1
0/
1#
#246
1/
#250
0#
b10 '
b10 -
#255
b0 !
b0 1
0/
1#
#256
1/
#260
0#
b11 '
b11 -
#265
0/
1#
#266
1/
#270
0D
1>
0#
b111010 %
b111010 +
b111010 4
b111010 :
b111010 @
b111010 F
b10011101001111101110100110100100 )
b10 (
b10 .
b0 '
b0 -
#275
b100001 !
b100001 1
0/
1#
#276
b111010 A
b111010 C
1/
#280
0#
#285
0/
1#
#286
1/
#290
0#
b1 &
b1 ,
#295
b11011011 "
b11011011 0
0/
1#
#296
1/
#300
0#
b10 &
b10 ,
#305
b111010 "
b111010 0
0/
1#
#306
1/
#310
0#
b11 &
b11 ,
#315
b0 "
b0 0
0/
1#
#316
1/
#320
0#
b0 &
b0 ,
#325
b100001 "
b100001 0
0/
1#
#326
1/
#330
0#
b1 '
b1 -
#335
b11011011 !
b11011011 1
0/
1#
#336
1/
#340
0#
b10 '
b10 -
#345
b111010 !
b111010 1
0/
1#
#346
1/
#350
0#
b11 '
b11 -
#355
b0 !
b0 1
0/
1#
#356
1/
#360
0>
18
0#
b1101 %
b1101 +
b1101 4
b1101 :
b1101 @
b1101 F
b110111000100110110001010101 )
b1 (
b1 .
b0 '
b0 -
#365
b100001 !
b100001 1
0/
1#
#366
b1101 ;
b1101 =
1/
#370
0#
#375
0/
1#
#376
1/
#380
0#
b1 &
b1 ,
#385
b11011011 "
b11011011 0
0/
1#
#386
1/
#390
0#
b10 &
b10 ,
#395
b111010 "
b111010 0
0/
1#
#396
1/
#400
0#
b11 &
b11 ,
#405
b1101 "
b1101 0
0/
1#
#406
1/
#410
0#
b0 &
b0 ,
#415
b100001 "
b100001 0
0/
1#
#416
1/
#420
0#
b1 '
b1 -
#425
b11011011 !
b11011011 1
0/
1#
#426
1/
#430
0#
b10 '
b10 -
#435
b111010 !
b111010 1
0/
1#
#436
1/
#440
0#
b11 '
b11 -
#445
b1101 !
b1101 1
0/
1#
#446
1/
#450
12
1D
1>
08
0#
b1110 (
b1110 .
b1101111001001100001000100010010 )
b11 $
b11 *
b11 3
b11 9
b11 ?
b11 E
b0 '
b0 -
#455
b100001 !
b100001 1
0/
1#
#456
b111011 A
b111011 C
b11011100 G
b11011100 I
b100010 5
b100010 7
1/
#460
02
0D
0>
0#
b0 (
b0 .
#465
b100010 !
b100010 1
b100010 "
b100010 0
0/
1#
#466
1/
#470
0#
b1 &
b1 ,
#475
b11011100 "
b11011100 0
0/
1#
#476
1/
#480
0#
b10 &
b10 ,
#485
b111011 "
b111011 0
0/
1#
#486
1/
#490
0#
b11 &
b11 ,
#495
b1101 "
b1101 0
0/
1#
#496
1/
#500
1>
0#
b10 (
b10 .
b1011010111001010101101011 )
b0 &
b0 ,
#505
b100010 "
b100010 0
0/
1#
#506
b111100 A
b111100 C
1/
#510
0>
0#
b0 (
b0 .
#515
0/
1#
#516
1/
#520
0#
b1 &
b1 ,
#525
b11011100 "
b11011100 0
0/
1#
#526
1/
#530
0#
b10 &
b10 ,
#535
b111100 "
b111100 0
0/
1#
#536
1/
#540
0#
b11 &
b11 ,
#545
b1101 "
b1101 0
0/
1#
#546
1/
#550
12
1D
1>
0#
b1110 (
b1110 .
b101111001010000001010110110000 )
b0 &
b0 ,
#555
b100010 "
b100010 0
0/
1#
#556
b111101 A
b111101 C
b11011101 G
b11011101 I
b100011 5
b100011 7
1/
#560
02
0D
0>
0#
b0 (
b0 .
#565
b100011 !
b100011 1
b100011 "
b100011 0
0/
1#
#566
1/
#570
0#
b1 &
b1 ,
#575
b11011101 "
b11011101 0
0/
1#
#576
1/
#580
0#
b10 &
b10 ,
#585
b111101 "
b111101 0
0/
1#
#586
1/
#590
0#
b11 &
b11 ,
#595
b1101 "
b1101 0
0/
1#
#596
1/
#600
1>
18
0#
b11 (
b11 .
b11100001111000110100110111110001 )
b0 &
b0 ,
#605
b100011 "
b100011 0
0/
1#
#606
b1110 ;
b1110 =
b111110 A
b111110 C
1/
#610
0>
08
0#
b0 (
b0 .
#615
0/
1#
#616
1/
#620
0#
b1 &
b1 ,
#625
b11011101 "
b11011101 0
0/
1#
#626
1/
#630
0#
b10 &
b10 ,
#635
b111110 "
b111110 0
0/
1#
#636
1/
#640
0#
b11 &
b11 ,
#645
b1110 "
b1110 0
0/
1#
#646
1/
#650
1D
1>
18
0#
b111 (
b111 .
b10111011111010111010011011111110 )
b0 &
b0 ,
#655
b100011 "
b100011 0
0/
1#
#656
b111111 A
b111111 C
b11011110 G
b11011110 I
b1111 ;
b1111 =
1/
#660
0D
0>
08
0#
b0 (
b0 .
#665
0/
1#
#666
1/
#670
0#
b1 &
b1 ,
#675
b11011110 "
b11011110 0
0/
1#
#676
1/
#680
0#
b10 &
b10 ,
#685
b111111 "
b111111 0
0/
1#
#686
1/
#690
0#
b11 &
b11 ,
#695
b1111 "
b1111 0
0/
1#
#696
1/
#700
1D
0#
b100 (
b100 .
b11010001011011001111101100111 )
b0 &
b0 ,
#705
b100011 "
b100011 0
0/
1#
#706
b11011111 G
b11011111 I
1/
#710
0D
0#
b0 (
b0 .
#715
0/
1#
#716
1/
#720
0#
b1 &
b1 ,
#725
b11011111 "
b11011111 0
0/
1#
#726
1/
#730
0#
b10 &
b10 ,
#735
b111111 "
b111111 0
0/
1#
#736
1/
#740
0#
b11 &
b11 ,
#745
b1111 "
b1111 0
0/
1#
#746
1/
#750
12
1D
1>
0#
b1110 (
b1110 .
b11100111000001111110000001111100 )
b0 &
b0 ,
#755
b100011 "
b100011 0
0/
1#
#756
b1000000 A
b1000000 C
b11100000 G
b11100000 I
b100100 5
b100100 7
1/
#760
02
0D
0>
0#
b0 (
b0 .
#765
b100100 !
b100100 1
b100100 "
b100100 0
0/
1#
#766
1/
#770
0#
b1 &
b1 ,
#775
b11100000 "
b11100000 0
0/
1#
#776
1/
#780
0#
b10 &
b10 ,
#785
b1000000 "
b1000000 0
0/
1#
#786
1/
#790
0#
b11 &
b11 ,
#795
b1111 "
b1111 0
0/
1#
#796
1/
#800
0#
b1001000001100010000111101001101 )
b0 &
b0 ,
#805
b100100 "
b100100 0
0/
1#
#806
1/
#810
0#
#815
0/
1#
#816
1/
#820
0#
b1 &
b1 ,
#825
b11100000 "
b11100000 0
0/
1#
#826
1/
#830
0#
b10 &
b10 ,
#835
b1000000 "
b1000000 0
0/
1#
#836
1/
#840
0#
b11 &
b11 ,
#845
b1111 "
b1111 0
0/
1#
#846
1/
#850
12
0#
b1000 (
b1000 .
b1011100010111010010100110101010 )
b0 &
b0 ,
#855
b100100 "
b100100 0
0/
1#
#856
b100101 5
b100101 7
1/
#860
02
0#
b0 (
b0 .
#865
b100101 !
b100101 1
b100101 "
b100101 0
0/
1#
#866
1/
#870
0#
b1 &
b1 ,
#875
b11100000 "
b11100000 0
0/
1#
#876
1/
#880
0#
b10 &
b10 ,
#885
b1000000 "
b1000000 0
0/
1#
#886
1/
#890
0#
b11 &
b11 ,
#895
b1111 "
b1111 0
0/
1#
#896
1/
#900
1D
1>
0#
b110 (
b110 .
b11011011011000011111111100100011 )
b0 &
b0 ,
#905
b100101 "
b100101 0
0/
1#
#906
b11100001 G
b11100001 I
b1000001 A
b1000001 C
1/
#910
0D
0>
0#
b0 (
b0 .
#915
0/
1#
#916
1/
#920
0#
b1 &
b1 ,
#925
b11100001 "
b11100001 0
0/
1#
#926
1/
#930
0#
b10 &
b10 ,
#935
b1000001 "
b1000001 0
0/
1#
#936
1/
#940
0#
b11 &
b11 ,
#945
b1111 "
b1111 0
0/
1#
#946
1/
#950
12
1D
18
0#
b1101 (
b1101 .
b10100110100100010001011000001000 )
b0 &
b0 ,
#955
b100101 "
b100101 0
0/
1#
#956
b11100010 G
b11100010 I
b100110 5
b100110 7
b10000 ;
b10000 =
1/
#960
02
0D
08
0#
b0 (
b0 .
#965
b100110 !
b100110 1
b100110 "
b100110 0
0/
1#
#966
1/
#970
0#
b1 &
b1 ,
#975
b11100010 "
b11100010 0
0/
1#
#976
1/
#980
0#
b10 &
b10 ,
#985
b1000001 "
b1000001 0
0/
1#
#986
1/
#990
0#
b11 &
b11 ,
#995
b10000 "
b10000 0
0/
1#
#996
1/
#1000
12
1D
0#
b1100 (
b1100 .
b11010110010101010000110001101001 )
b0 &
b0 ,
#1005
b100110 "
b100110 0
0/
1#
#1006
b100111 5
b100111 7
b11100011 G
b11100011 I
1/
#1010
02
0D
0#
b0 (
b0 .
#1015
b100111 !
b100111 1
b100111 "
b100111 0
0/
1#
#1016
1/
#1020
0#
b1 &
b1 ,
#1025
b11100011 "
b11100011 0
0/
1#
#1026
1/
#1030
0#
b10 &
b10 ,
#1035
b1000001 "
b1000001 0
0/
1#
#1036
1/
#1040
0#
b11 &
b11 ,
#1045
b10000 "
b10000 0
0/
1#
#1046
1/
#1050
0#
b1001010100010100010110 )
b0 &
b0 ,
#1055
b100111 "
b100111 0
0/
1#
#1056
1/
#1060
0#
#1065
0/
1#
#1066
1/
#1070
0#
b1 &
b1 ,
#1075
b11100011 "
b11100011 0
0/
1#
#1076
1/
#1080
0#
b10 &
b10 ,
#1085
b1000001 "
b1000001 0
0/
1#
#1086
1/
#1090
0#
b11 &
b11 ,
#1095
b10000 "
b10000 0
0/
1#
#1096
1/
#1100
12
1D
1>
0#
b1110 (
b1110 .
b1000111011100000111000010011111 )
b0 &
b0 ,
#1105
b100111 "
b100111 0
0/
1#
#1106
b101000 5
b101000 7
b11100100 G
b11100100 I
b1000010 A
b1000010 C
1/
#1110
02
0D
0>
0#
b0 (
b0 .
#1115
b101000 !
b101000 1
b101000 "
b101000 0
0/
1#
#1116
1/
#1120
0#
b1 &
b1 ,
#1125
b11100100 "
b11100100 0
0/
1#
#1126
1/
#1130
0#
b10 &
b10 ,
#1135
b1000010 "
b1000010 0
0/
1#
#1136
1/
#1140
0#
b11 &
b11 ,
#1145
b10000 "
b10000 0
0/
1#
#1146
1/
#1150
1D
1>
0#
b110 (
b110 .
b1011011011000010100001001010100 )
b0 &
b0 ,
#1155
b101000 "
b101000 0
0/
1#
#1156
b1000011 A
b1000011 C
b11100101 G
b11100101 I
1/
#1160
0D
0>
0#
b0 (
b0 .
#1165
0/
1#
#1166
1/
#1170
0#
b1 &
b1 ,
#1175
b11100101 "
b11100101 0
0/
1#
#1176
1/
#1180
0#
b10 &
b10 ,
#1185
b1000011 "
b1000011 0
0/
1#
#1186
1/
#1190
0#
b11 &
b11 ,
#1195
b10000 "
b10000 0
0/
1#
#1196
1/
#1200
12
1D
1>
18
0#
b1111 (
b1111 .
b1011111100101000110000101000101 )
b10 $
b10 *
b10 3
b10 9
b10 ?
b10 E
b0 &
b0 ,
#1205
b101000 "
b101000 0
0/
1#
#1206
b1111 ;
b1111 =
b100111 5
b100111 7
b11100100 G
b11100100 I
b1000010 A
b1000010 C
1/
#1210
02
0D
0>
08
0#
b0 (
b0 .
#1215
b100111 !
b100111 1
b100111 "
b100111 0
0/
1#
#1216
1/
#1220
0#
b1 '
b1 -
#1225
b11100100 !
b11100100 1
0/
1#
#1226
1/
#1230
0#
b10 '
b10 -
#1235
b1000010 !
b1000010 1
0/
1#
#1236
1/
#1240
0#
b11 '
b11 -
#1245
b1111 !
b1111 1
0/
1#
#1246
1/
#1250
12
0#
b1000 (
b1000 .
b1110100000001110110010101000010 )
b0 '
b0 -
#1255
b100111 !
b100111 1
0/
1#
#1256
b100110 5
b100110 7
1/
#1260
02
0#
b0 (
b0 .
#1265
b100110 !
b100110 1
b100110 "
b100110 0
0/
1#
#1266
1/
#1270
0#
b1 '
b1 -
#1275
b11100100 !
b11100100 1
0/
1#
#1276
1/
#1280
0#
b10 '
b10 -
#1285
b1000010 !
b1000010 1
0/
1#
#1286
1/
#1290
0#
b11 '
b11 -
#1295
b1111 !
b1111 1
0/
1#
#1296
1/
#1300
12
1D
1>
0#
b1110 (
b1110 .
b10101111010100100110111111011011 )
b0 '
b0 -
#1305
b100110 !
b100110 1
0/
1#
#1306
b100101 5
b100101 7
b11100011 G
b11100011 I
b1000001 A
b1000001 C
1/
#1310
02
0D
0>
0#
b0 (
b0 .
#1315
b100101 !
b100101 1
b100101 "
b100101 0
0/
1#
#1316
1/
#1320
0#
b1 '
b1 -
#1325
b11100011 !
b11100011 1
0/
1#
#1326
1/
#1330
0#
b10 '
b10 -
#1335
b1000001 !
b1000001 1
0/
1#
#1336
1/
#1340
0#
b11 '
b11 -
#1345
b1111 !
b1111 1
0/
1#
#1346
1/
#1350
12
18
0#
b1001 (
b1001 .
b100100011001011000101100000 )
b0 '
b0 -
#1355
b100101 !
b100101 1
0/
1#
#1356
b100100 5
b100100 7
b1110 ;
b1110 =
1/
#1360
02
08
0#
b0 (
b0 .
#1365
b100100 !
b100100 1
b100100 "
b100100 0
0/
1#
#1366
1/
#1370
0#
b1 '
b1 -
#1375
b11100011 !
b11100011 1
0/
1#
#1376
1/
#1380
0#
b10 '
b10 -
#1385
b1000001 !
b1000001 1
0/
1#
#1386
1/
#1390
0#
b11 '
b11 -
#1395
b1110 !
b1110 1
0/
1#
#1396
1/
#1400
1D
1>
0#
b110 (
b110 .
b1111011000010111110100111100001 )
b0 '
b0 -
#1405
b100100 !
b100100 1
0/
1#
#1406
b11100010 G
b11100010 I
b1000000 A
b1000000 C
1/
#1410
0D
0>
0#
b0 (
b0 .
#1415
0/
1#
#1416
1/
#1420
0#
b1 '
b1 -
#1425
b11100010 !
b11100010 1
0/
1#
#1426
1/
#1430
0#
b10 '
b10 -
#1435
b1000000 !
b1000000 1
0/
1#
#1436
1/
#1440
0#
b11 '
b11 -
#1445
b1110 !
b1110 1
0/
1#
#1446
1/
#1450
12
1>
0#
b1010 (
b1010 .
b1101010010111011011000101110 )
b0 '
b0 -
#1455
b100100 !
b100100 1
0/
1#
#1456
b111111 A
b111111 C
b100011 5
b100011 7
1/
#1460
02
0>
0#
b0 (
b0 .
#1465
b100011 !
b100011 1
b100011 "
b100011 0
0/
1#
#1466
1/
#1470
0#
b1 '
b1 -
#1475
b11100010 !
b11100010 1
0/
1#
#1476
1/
#1480
0#
b10 '
b10 -
#1485
b111111 !
b111111 1
0/
1#
#1486
1/
#1490
0#
b11 '
b11 -
#1495
b1110 !
b1110 1
0/
1#
#1496
1/
#1500
12
0#
b1000 (
b1000 .
b110100000011110011100011010111 )
b0 '
b0 -
#1505
b100011 !
b100011 1
0/
1#
#1506
b100010 5
b100010 7
1/
#1510
02
0#
b0 (
b0 .
#1515
b100010 !
b100010 1
b100010 "
b100010 0
0/
1#
#1516
1/
#1520
0#
b1 '
b1 -
#1525
b11100010 !
b11100010 1
0/
1#
#1526
1/
#1530
0#
b10 '
b10 -
#1535
b111111 !
b111111 1
0/
1#
#1536
1/
#1540
0#
b11 '
b11 -
#1545
b1110 !
b1110 1
0/
1#
#1546
1/
#1550
12
1D
18
0#
b1101 (
b1101 .
b10101110111010100110111100101100 )
b0 '
b0 -
#1555
b100010 !
b100010 1
0/
1#
#1556
b11100001 G
b11100001 I
b100001 5
b100001 7
b1101 ;
b1101 =
1/
#1560
02
0D
08
0#
b0 (
b0 .
#1565
b100001 !
b100001 1
b100001 "
b100001 0
0/
1#
#1566
1/
#1570
0#
b1 '
b1 -
#1575
b11100001 !
b11100001 1
0/
1#
#1576
1/
#1580
0#
b10 '
b10 -
#1585
b111111 !
b111111 1
0/
1#
#1586
1/
#1590
0#
b11 '
b11 -
#1595
b1101 !
b1101 1
0/
1#
#1596
1/
#1600
18
0#
b1 (
b1 .
b1101000100011000100001000111101 )
b0 '
b0 -
#1605
b100001 !
b100001 1
0/
1#
#1606
b1100 ;
b1100 =
1/
#1610
08
0#
b0 (
b0 .
#1615
0/
1#
#1616
1/
#1620
0#
b1 '
b1 -
#1625
b11100001 !
b11100001 1
0/
1#
#1626
1/
#1630
0#
b10 '
b10 -
#1635
b111111 !
b111111 1
0/
1#
#1636
1/
#1640
0#
b11 '
b11 -
#1645
b1100 !
b1100 1
0/
1#
#1646
1/
#1650
1>
18
0#
b11 (
b11 .
b11001111010110010001111011010 )
b0 '
b0 -
#1655
b100001 !
b100001 1
0/
1#
#1656
b111110 A
b111110 C
b1011 ;
b1011 =
1/
#1660
0>
08
0#
b0 (
b0 .
#1665
0/
1#
#1666
1/
#1670
0#
b1 '
b1 -
#1675
b11100001 !
b11100001 1
0/
1#
#1676
1/
#1680
0#
b10 '
b10 -
#1685
b111110 !
b111110 1
0/
1#
#1686
1/
#1690
0#
b11 '
b11 -
#1695
b1011 !
b1011 1
0/
1#
#1696
1/
#1700
12
1>
18
0#
b1011 (
b1011 .
b11010101111101111100011110010011 )
b0 '
b0 -
#1705
b100001 !
b100001 1
0/
1#
#1706
b1010 ;
b1010 =
b100000 5
b100000 7
b111101 A
b111101 C
1/
#1710
02
0>
08
0#
b0 (
b0 .
#1715
b100000 !
b100000 1
b100000 "
b100000 0
0/
1#
#1716
1/
#1720
0#
b1 '
b1 -
#1725
b11100001 !
b11100001 1
0/
1#
#1726
1/
#1730
0#
b10 '
b10 -
#1735
b111101 !
b111101 1
0/
1#
#1736
1/
#1740
0#
b11 '
b11 -
#1745
b1010 !
b1010 1
0/
1#
#1746
1/
#1750
12
0#
b1000 (
b1000 .
b10110100001000000100011110111000 )
b0 '
b0 -
#1755
b100000 !
b100000 1
0/
1#
#1756
b11111 5
b11111 7
1/
#1760
02
0#
b0 (
b0 .
#1765
b11111 !
b11111 1
b11111 "
b11111 0
0/
1#
#1766
1/
#1770
0#
b1 '
b1 -
#1775
b11100001 !
b11100001 1
0/
1#
#1776
1/
#1780
0#
b10 '
b10 -
#1785
b111101 !
b111101 1
0/
1#
#1786
1/
#1790
0#
b11 '
b11 -
#1795
b1010 !
b1010 1
0/
1#
#1796
1/
#1800
1>
0#
b10 (
b10 .
b101001001101011100011001011001 )
b0 '
b0 -
#1805
b11111 !
b11111 1
0/
1#
#1806
b111100 A
b111100 C
1/
#1810
0>
0#
b0 (
b0 .
#1815
0/
1#
#1816
1/
#1820
0#
b1 '
b1 -
#1825
b11100001 !
b11100001 1
0/
1#
#1826
1/
#1830
0#
b10 '
b10 -
#1835
b111100 !
b111100 1
0/
1#
#1836
1/
#1840
0#
b11 '
b11 -
#1845
b1010 !
b1010 1
0/
1#
#1846
1/
#1850
1>
0#
b10 (
b10 .
b10000001011110110101101001000110 )
b0 '
b0 -
#1855
b11111 !
b11111 1
0/
1#
#1856
b111011 A
b111011 C
1/
#1860
0>
0#
b0 (
b0 .
#1865
0/
1#
#1866
1/
#1870
0#
b1 '
b1 -
#1875
b11100001 !
b11100001 1
0/
1#
#1876
1/
#1880
0#
b10 '
b10 -
#1885
b111011 !
b111011 1
0/
1#
#1886
1/
#1890
0#
b11 '
b11 -
#1895
b1010 !
b1010 1
0/
1#
#1896
1/
#1900
12
1>
18
0#
b1011 (
b1011 .
b1001101101000101101100000001111 )
b0 '
b0 -
#1905
b11111 !
b11111 1
0/
1#
#1906
b1001 ;
b1001 =
b11110 5
b11110 7
b111010 A
b111010 C
1/
#1910
02
0>
08
0#
b0 (
b0 .
#1915
b11110 !
b11110 1
b11110 "
b11110 0
0/
1#
#1916
1/
#1920
0#
b1 '
b1 -
#1925
b11100001 !
b11100001 1
0/
1#
#1926
1/
#1930
0#
b10 '
b10 -
#1935
b111010 !
b111010 1
0/
1#
#1936
1/
#1940
0#
b11 '
b11 -
#1945
b1001 !
b1001 1
0/
1#
#1946
1/
#1950
0#
b0 '
b0 -
