Project1/part1.v
module register #(
parameter NBits = 16
) (
  input               clk,
  input[1:0]          funsel, 
  input               e, 
  input[NBits-1: 0]   i,
  output[NBits-1: 0]  q
);

reg[NBits-1:0] data;
assign q = data;

always @(posedge clk) begin
  if (e)
    case (funsel)
      2'b00: data = {NBits{1'b0}};  // Clear
      2'b01: data = i;              // Load
      2'b10: data = data - 1'b1;    // Decrement
      2'b11: data = data + 1'b1;    // Increment
    endcase
end 

endmodule

Project1/part2a.v
`include "part1.v"

module IR_16_bit (
  input         clk,
  input[7:0]    i_half,
  input[1:0]    funsel,
  input         e,
  input         l_h,
  output[15:0]  ir_out
);

reg[15:0] i;
reg dclk;

register #(.NBits(16)) ir_low (
  .clk    (dclk),
  .funsel (funsel ),
  .e      (e      ),
  .i      (i      ),
  .q      (ir_out )
);

always @(posedge clk) begin
  dclk = 0;
  if (e & funsel == 2'b01)
    if (l_h)
      i[15:8] = i_half;
    else
      i[7:0] = i_half;
  else 
    i = ir_out;
  #1;
  dclk = 1;
end 

endmodule

Project1/part2a_tb.v
`include "part2a.v"

module part2a_tb;
reg clk;
reg[7:0] i_half;
reg[1:0] funsel;
reg e, l_h;
wire[15:0] ir_out;

IR_16_bit uut(
  .clk    (clk    ),
  .i_half (i_half ),
  .funsel (funsel ),
  .e      (e      ),
  .l_h    (l_h    ),
  .ir_out (ir_out )
);

always #5 clk = ~clk;

task displayHead;
  $display("%6s %6s %6s %6s %6s %6s", "Clock", "Enable", "L'/H", "FunSel","Input","Output");
endtask

task displayLine;
  $display({50{"-"}});
endtask

task load(input[7:0] a, input[7:0] b);
begin
  funsel = 2'b00; 
  #10;

  funsel = 2'b01;
  l_h = 1'b0; i_half = b;
  #10;

  l_h = 1'b1; i_half = a;
  #10;
end
endtask;

initial begin
  $dumpfile("dump.vcd"); $dumpvars;
  $display("Testing 16-bit instruction register");
  $monitor("%6b %6b %6b %6b   0x%h 0x%h%h", clk, e, l_h, funsel, i_half, ir_out[15:8], ir_out[7:0]);
  e = 1'b1; 
  clk = 0;

  $display("\nLoad & clear test");
  displayLine;
  displayHead;
  load(8'h33, 8'haa);
  displayLine;
  displayHead;
  load(8'h4c, 8'h4c);
  displayLine;
  displayHead;
  load(8'h66, 8'h55);
  displayLine;
  displayHead;
  load(8'h01, 8'hf0);
  displayLine;

  $display("\nIncrement test");
  displayLine;
  displayHead;
  funsel = 2'b00; #10;
  funsel = 2'b11;
  #100;

  $display("\nDecrement test");
  displayLine;
  displayHead;
  funsel = 2'b00; #10;
  funsel = 2'b10;
  #100;
  $finish;
end

endmodule

Project1/dump.vcd
$date
	Thu Apr 13 12:38:06 2023
$end
$version
	Icarus Verilog
$end
$timescale
	1s
$end
$scope module part2a_tb $end
$var wire 16 ! ir_out [15:0] $end
$var reg 1 " clk $end
$var reg 1 # e $end
$var reg 2 $ funsel [1:0] $end
$var reg 8 % i_half [7:0] $end
$var reg 1 & l_h $end
$scope module uut $end
$var wire 1 " clk $end
$var wire 1 # e $end
$var wire 2 ' funsel [1:0] $end
$var wire 8 ( i_half [7:0] $end
$var wire 1 & l_h $end
$var wire 16 ) ir_out [15:0] $end
$var reg 1 * dclk $end
$var reg 16 + i [15:0] $end
$scope module ir_low $end
$var wire 1 * clk $end
$var wire 1 # e $end
$var wire 2 , funsel [1:0] $end
$var wire 16 - i [15:0] $end
$var wire 16 . q [15:0] $end
$var parameter 32 / NBits $end
$var reg 16 0 data [15:0] $end
$upscope $end
$upscope $end
$scope task displayHead $end
$upscope $end
$scope task displayLine $end
$upscope $end
$scope task load $end
$var reg 8 1 a [7:0] $end
$var reg 8 2 b [7:0] $end
$upscope $end
$upscope $end
$enddefinitions $end
$comment Show the parameter values. $end
$dumpall
b10000 /
$end
#0
$dumpvars
b10101010 2
b110011 1
bx 0
bx .
bx -
b0 ,
bx +
x*
bx )
bx (
b0 '
x&
bx %
b0 $
1#
0"
bx !
$end
#5
0*
1"
#6
b0 !
b0 )
b0 .
b0 0
1*
#10
0"
b10101010 %
b10101010 (
0&
b1 $
b1 '
b1 ,
#15
bx10101010 +
bx10101010 -
0*
1"
#16
bx10101010 !
bx10101010 )
bx10101010 .
bx10101010 0
1*
#20
0"
b110011 %
b110011 (
1&
#25
b11001110101010 +
b11001110101010 -
0*
1"
#26
b11001110101010 !
b11001110101010 )
b11001110101010 .
b11001110101010 0
1*
#30
0"
b0 $
b0 '
b0 ,
b1001100 2
b1001100 1
#35
0*
1"
#36
b0 !
b0 )
b0 .
b0 0
1*
#40
0"
b1001100 %
b1001100 (
0&
b1 $
b1 '
b1 ,
#45
b11001101001100 +
b11001101001100 -
0*
1"
#46
b11001101001100 !
b11001101001100 )
b11001101001100 .
b11001101001100 0
1*
#50
0"
1&
#55
b100110001001100 +
b100110001001100 -
0*
1"
#56
b100110001001100 !
b100110001001100 )
b100110001001100 .
b100110001001100 0
1*
#60
0"
b0 $
b0 '
b0 ,
b1010101 2
b1100110 1
#65
0*
1"
#66
b0 !
b0 )
b0 .
b0 0
1*
#70
0"
b1010101 %
b1010101 (
0&
b1 $
b1 '
b1 ,
#75
b100110001010101 +
b100110001010101 -
0*
1"
#76
b100110001010101 !
b100110001010101 )
b100110001010101 .
b100110001010101 0
1*
#80
0"
b1100110 %
b1100110 (
1&
#85
b110011001010101 +
b110011001010101 -
0*
1"
#86
b110011001010101 !
b110011001010101 )
b110011001010101 .
b110011001010101 0
1*
#90
0"
b0 $
b0 '
b0 ,
b11110000 2
b1 1
#95
0*
1"
#96
b0 !
b0 )
b0 .
b0 0
1*
#100
0"
b11110000 %
b11110000 (
0&
b1 $
b1 '
b1 ,
#105
b110011011110000 +
b110011011110000 -
0*
1"
#106
b110011011110000 !
b110011011110000 )
b110011011110000 .
b110011011110000 0
1*
#110
0"
b1 %
b1 (
1&
#115
b111110000 +
b111110000 -
0*
1"
#116
b111110000 !
b111110000 )
b111110000 .
b111110000 0
1*
#120
0"
b0 $
b0 '
b0 ,
#125
0*
1"
#126
b0 !
b0 )
b0 .
b0 0
1*
#130
0"
b11 $
b11 '
b11 ,
#135
b0 +
b0 -
0*
1"
#136
b1 !
b1 )
b1 .
b1 0
1*
#140
0"
#145
b1 +
b1 -
0*
1"
#146
b10 !
b10 )
b10 .
b10 0
1*
#150
0"
#155
b10 +
b10 -
0*
1"
#156
b11 !
b11 )
b11 .
b11 0
1*
#160
0"
#165
b11 +
b11 -
0*
1"
#166
b100 !
b100 )
b100 .
b100 0
1*
#170
0"
#175
b100 +
b100 -
0*
1"
#176
b101 !
b101 )
b101 .
b101 0
1*
#180
0"
#185
b101 +
b101 -
0*
1"
#186
b110 !
b110 )
b110 .
b110 0
1*
#190
0"
#195
b110 +
b110 -
0*
1"
#196
b111 !
b111 )
b111 .
b111 0
1*
#200
0"
#205
b111 +
b111 -
0*
1"
#206
b1000 !
b1000 )
b1000 .
b1000 0
1*
#210
0"
#215
b1000 +
b1000 -
0*
1"
#216
b1001 !
b1001 )
b1001 .
b1001 0
1*
#220
0"
#225
b1001 +
b1001 -
0*
1"
#226
b1010 !
b1010 )
b1010 .
b1010 0
1*
#230
0"
b0 $
b0 '
b0 ,
#235
b1010 +
b1010 -
0*
1"
#236
b0 !
b0 )
b0 .
b0 0
1*
#240
0"
b10 $
b10 '
b10 ,
#245
b0 +
b0 -
0*
1"
#246
b1111111111111111 !
b1111111111111111 )
b1111111111111111 .
b1111111111111111 0
1*
#250
0"
#255
b1111111111111111 +
b1111111111111111 -
0*
1"
#256
b1111111111111110 !
b1111111111111110 )
b1111111111111110 .
b1111111111111110 0
1*
#260
0"
#265
b1111111111111110 +
b1111111111111110 -
0*
1"
#266
b1111111111111101 !
b1111111111111101 )
b1111111111111101 .
b1111111111111101 0
1*
#270
0"
#275
b1111111111111101 +
b1111111111111101 -
0*
1"
#276
b1111111111111100 !
b1111111111111100 )
b1111111111111100 .
b1111111111111100 0
1*
#280
0"
#285
b1111111111111100 +
b1111111111111100 -
0*
1"
#286
b1111111111111011 !
b1111111111111011 )
b1111111111111011 .
b1111111111111011 0
1*
#290
0"
#295
b1111111111111011 +
b1111111111111011 -
0*
1"
#296
b1111111111111010 !
b1111111111111010 )
b1111111111111010 .
b1111111111111010 0
1*
#300
0"
#305
b1111111111111010 +
b1111111111111010 -
0*
1"
#306
b1111111111111001 !
b1111111111111001 )
b1111111111111001 .
b1111111111111001 0
1*
#310
0"
#315
b1111111111111001 +
b1111111111111001 -
0*
1"
#316
b1111111111111000 !
b1111111111111000 )
b1111111111111000 .
b1111111111111000 0
1*
#320
0"
#325
b1111111111111000 +
b1111111111111000 -
0*
1"
#326
b1111111111110111 !
b1111111111110111 )
b1111111111110111 .
b1111111111110111 0
1*
#330
0"
#335
b1111111111110111 +
b1111111111110111 -
0*
1"
#336
b1111111111110110 !
b1111111111110110 )
b1111111111110110 .
b1111111111110110 0
1*
